keras_spark/__init__.py
keras_spark/core.py
keras_spark/models.py
keras_spark/test_core.py
keras_spark/test_model.py
keras_spark/utils.py
keras_spark-0.99.dist-info/LICENSE.txt
keras_spark-0.99.dist-info/METADATA
keras_spark-0.99.dist-info/WHEEL
keras_spark-0.99.dist-info/top_level.txt
keras_spark-0.99.dist-info/RECORD
