Metadata-Version: 2.1
Name: keras_spark
Version: 0.99
Summary: seamless support for spark datasets in keras .fit() and .predict()
Author: christian sommeregger
Author-email: csommeregger@gmail.com
License-File: LICENSE.txt
Requires-Dist: pandas (==2.1.1)
Requires-Dist: pyarrow (==7.0.0)
Requires-Dist: tensorflow (<=2.12.0)
Requires-Dist: petastorm
Requires-Dist: s3fs
